django_ragamuffin/__init__.py
django_ragamuffin/admin.py
django_ragamuffin/apps.py
django_ragamuffin/db_routers.py
django_ragamuffin/forms.py
django_ragamuffin/mathpix.py
django_ragamuffin/models.py
django_ragamuffin/nuke.py
django_ragamuffin/remote_calls.py
django_ragamuffin/settings.py
django_ragamuffin/signals.py
django_ragamuffin/urls.py
django_ragamuffin/util.py
django_ragamuffin/utils.py
django_ragamuffin/views.py
django_ragamuffin/migrations/0001_initial.py
django_ragamuffin/migrations/0002_modechoice_mode.py
django_ragamuffin/migrations/0003_assistant_mode_choice.py
django_ragamuffin/migrations/0004_alter_assistant_mode_choice.py
django_ragamuffin/migrations/0005_alter_openaifile_file.py
django_ragamuffin/migrations/0006_message.py
django_ragamuffin/migrations/0007_alter_message_thread.py
django_ragamuffin/migrations/0008_message_choice_message_comment.py
django_ragamuffin/migrations/0009_rename_ntoken_message_ntokens.py
django_ragamuffin/migrations/0010_alter_message_comment_alter_message_mhash_and_more.py
django_ragamuffin/migrations/0011_alter_message_date.py
django_ragamuffin/migrations/0012_alter_message_choice.py
django_ragamuffin/migrations/0013_remove_thread_messages.py
django_ragamuffin/migrations/0014_message_subdomain.py
django_ragamuffin/migrations/0015_quser_subdomain.py
django_ragamuffin/migrations/0016_quser_unique_username_subdomain.py
django_ragamuffin/migrations/__init__.py
django_ragamuffin/node_modules/katex/src/fonts/generate_fonts.py
django_ragamuffin/node_modules/katex/src/metrics/extract_tfms.py
django_ragamuffin/node_modules/katex/src/metrics/extract_ttfs.py
django_ragamuffin/node_modules/katex/src/metrics/format_json.py
django_ragamuffin/node_modules/katex/src/metrics/parse_tfm.py
django_ragamuffin/static/django_ragamuffin/script.js
django_ragamuffin/templates/django_ragamuffin/edit_assistant.html
django_ragamuffin/templates/django_ragamuffin/query_form.html
django_ragamuffin/templates/django_ragamuffin/upload.html
django_ragamuffin-1.107.1.24.dist-info/METADATA
django_ragamuffin-1.107.1.24.dist-info/WHEEL
django_ragamuffin-1.107.1.24.dist-info/top_level.txt
django_ragamuffin-1.107.1.24.dist-info/RECORD
